__init__.py
realai.py
realai-0.1.3.dist-info/LICENSE
realai-0.1.3.dist-info/METADATA
realai-0.1.3.dist-info/WHEEL
realai-0.1.3.dist-info/top_level.txt
realai-0.1.3.dist-info/RECORD
