Metadata-Version: 2.1
Name: realai
Version: 0.1.3
Summary: The official SDK for RealAI
Author-email: Adrian <adrianl@realai.se>
License: MIT License
Project-URL: Homepage, https://github.com/RealAISwe/realai-sdk
Requires-Python: >=3.7
License-File: LICENSE
